django_postgres_partitioning/__init__.py
django_postgres_partitioning/partitioning.sql
django_postgres_partitioning/triggers.sql
django_postgres_partitioning/management/__init__.py
django_postgres_partitioning/management/commands/__init__.py
django_postgres_partitioning/management/commands/apply_partitioning.py
django_postgres_partitioning/management/commands/clear_table.py
django_postgres_partitioning/management/commands/split_table.py
django_postgres_partitioning-1.1.1.dist-info/METADATA
django_postgres_partitioning-1.1.1.dist-info/WHEEL
django_postgres_partitioning-1.1.1.dist-info/dependency_links.txt
django_postgres_partitioning-1.1.1.dist-info/top_level.txt
django_postgres_partitioning-1.1.1.dist-info/RECORD
